remotelib/__init__.py
remotelib/remote_db.py
remotelib/remote_exec.py
remotelib/route53.py
remotelib/server_htpass.py
remotelib/ssh_tunnel.py
rxpipe-0.7.0.dist-info/METADATA
rxpipe-0.7.0.dist-info/WHEEL
rxpipe-0.7.0.dist-info/top_level.txt
rxpipe-0.7.0.dist-info/RECORD
