Metadata-Version: 2.1
Name: rxpipe
Version: 0.7.0
Summary: Wrappers for remote exec, local exec.
Home-page: http://vixal.net
Author: James M
Author-email: jimferd@gmail.com
License: UNKNOWN
Platform: UNKNOWN
Classifier: Programming Language :: Python :: 3
Classifier: License :: OSI Approved :: MIT License
Classifier: Operating System :: OS Independent
